Workbook

Sheet Read me
A1: Portfolio WACI – sample calculation
A2: A step-by-step worked example of how the portfolio carbon intensity calculator (v1) works. Every result is a live formula, so you can change the inputs and watch the numbers update.
A4: HOW TO USE
A5: 1. Go to the 'WACI calculation' tab.
A6: 2. Replace the blue cells on the yellow background with your own funds (up to 10 rows). Leave a WACI cell blank if the fund doesn't publish one.
A7: 3. Read the results in the green box. The 'How it works' tab explains each step with the example's own numbers.
A9: COLOUR KEY
A10: Blue text on yellow = inputs you can change. Black text = formulas (don't edit). Green text = values linked from another tab. Green box = results.
A12: RULES THE CALCULATION FOLLOWS
A13: • Portfolio WACI = sum of (each fund's rescaled share × its WACI). Shares are rescaled over the funds that have a figure, so they add up to 100%.
A14: • Scope 1+2 and Scope 1+2+3 are calculated separately and never combined.
A15: • Figures are used exactly as published. There is no currency conversion: if some funds report per $1m and others per €1m of revenue, the result is flagged as mixed and approximate.
... A23: For information only, not investment advice. Built 5 October 2026.

Sheet WACI calculation
A1: Portfolio WACI – sample calculation
A2: Change the blue cells. Everything else updates automatically.
A4: Amounts are in: | B4: EUR | C4: Enter every amount in this currency, as your bank or broker shows it.
A5: Step 1 – Your funds (inputs) | I5: Step 2 – Scope 1+2 working | N5: Step 3 – Scope 1+2+3 working
A6: Fund name | B6: ="Amount ("&$B$4&")" -> Amount (EUR) | C6: WACI Scope 1+2 | D6: WACI Scope 1+2+3 | E6: WACI is per (USD / EUR revenue) | F6: Data coverage | G6: Figure date | I6: Has a figure? (1 = yes) | J6: Value included | K6: Rescaled share | L6: Contribution (share × WACI) | N6: Has a figure? (1 = yes) | O6: Value included | P6: Rescaled share | Q6: Contribution (share × WACI)
A7: Example Global Equity Fund | B7: 10000 | C7: 95 | D7: 620 | E7: USD | F7: 0.99 | G7: 46265 | I7: =IF(AND(N(B7)>0,N(C7)>0),1,0) -> 1 | J7: =IF(I7=1,B7,0) -> 10000 | K7: =IF($J$17>0,J7/$J$17,0) -> 0.44444444 | L7: =K7*IF(I7=1,C7,0) -> 42.222222 | N7: =IF(AND(N(B7)>0,N(D7)>0),1,0) -> 1 | O7: =IF(N7=1,B7,0) -> 10000 | P7: =IF($O$17>0,O7/$O$17,0) -> 0.71428571 | Q7: =P7*IF(N7=1,D7,0) -> 442.85714
A8: Example Europe Equity Fund | B8: 6000 | C8: 80 | E8: USD | F8: 1 | G8: 46265 | I8: =IF(AND(N(B8)>0,N(C8)>0),1,0) -> 1 | J8: =IF(I8=1,B8,0) -> 6000 | K8: =IF($J$17>0,J8/$J$17,0) -> 0.26666667 | L8: =K8*IF(I8=1,C8,0) -> 21.333333 | N8: =IF(AND(N(B8)>0,N(D8)>0),1,0) -> 0 | O8: =IF(N8=1,B8,0) -> 0 | P8: =IF($O$17>0,O8/$O$17,0) -> 0 | Q8: =P8*IF(N8=1,D8,0) -> 0
A9: Example Emerging Markets Fund | B9: 4000 | C9: 260 | D9: 1150 | E9: USD | F9: 0.95 | G9: 46234 | I9: =IF(AND(N(B9)>0,N(C9)>0),1,0) -> 1 | J9: =IF(I9=1,B9,0) -> 4000 | K9: =IF($J$17>0,J9/$J$17,0) -> 0.17777778 | L9: =K9*IF(I9=1,C9,0) -> 46.222222 | N9: =IF(AND(N(B9)>0,N(D9)>0),1,0) -> 1 | O9: =IF(N9=1,B9,0) -> 4000 | P9: =IF($O$17>0,O9/$O$17,0) -> 0.28571429 | Q9: =P9*IF(N9=1,D9,0) -> 328.57143
A10: Example Clean Energy Fund | B10: 2500 | C10: 140 | E10: USD | F10: 0.92 | G10: 46203 | I10: =IF(AND(N(B10)>0,N(C10)>0),1,0) -> 1 | J10: =IF(I10=1,B10,0) -> 2500 | K10: =IF($J$17>0,J10/$J$17,0) -> 0.11111111 | L10: =K10*IF(I10=1,C10,0) -> 15.555556 | N10: =IF(AND(N(B10)>0,N(D10)>0),1,0) -> 0 | O10: =IF(N10=1,B10,0) -> 0 | P10: =IF($O$17>0,O10/$O$17,0) -> 0 | Q10: =P10*IF(N10=1,D10,0) -> 0
A11: Example Bond Fund | B11: 2000 | E11: USD | I11: =IF(AND(N(B11)>0,N(C11)>0),1,0) -> 0 | J11: =IF(I11=1,B11,0) -> 0 | K11: =IF($J$17>0,J11/$J$17,0) -> 0 | L11: =K11*IF(I11=1,C11,0) -> 0 | N11: =IF(AND(N(B11)>0,N(D11)>0),1,0) -> 0 | O11: =IF(N11=1,B11,0) -> 0 | P11: =IF($O$17>0,O11/$O$17,0) -> 0 | Q11: =P11*IF(N11=1,D11,0) -> 0
I12: =IF(AND(N(B12)>0,N(C12)>0),1,0) -> 0 | J12: =IF(I12=1,B12,0) -> 0 | K12: =IF($J$17>0,J12/$J$17,0) -> 0 | L12: =K12*IF(I12=1,C12,0) -> 0 | N12: =IF(AND(N(B12)>0,N(D12)>0),1,0) -> 0 | O12: =IF(N12=1,B12,0) -> 0 | P12: =IF($O$17>0,O12/$O$17,0) -> 0 | Q12: =P12*IF(N12=1,D12,0) -> 0
I13: =IF(AND(N(B13)>0,N(C13)>0),1,0) -> 0 | J13: =IF(I13=1,B13,0) -> 0 | K13: =IF($J$17>0,J13/$J$17,0) -> 0 | L13: =K13*IF(I13=1,C13,0) -> 0 | N13: =IF(AND(N(B13)>0,N(D13)>0),1,0) -> 0 | O13: =IF(N13=1,B13,0) -> 0 | P13: =IF($O$17>0,O13/$O$17,0) -> 0 | Q13: =P13*IF(N13=1,D13,0) -> 0
I14: =IF(AND(N(B14)>0,N(C14)>0),1,0) -> 0 | J14: =IF(I14=1,B14,0) -> 0 | K14: =IF($J$17>0,J14/$J$17,0) -> 0 | L14: =K14*IF(I14=1,C14,0) -> 0 | N14: =IF(AND(N(B14)>0,N(D14)>0),1,0) -> 0 | O14: =IF(N14=1,B14,0) -> 0 | P14: =IF($O$17>0,O14/$O$17,0) -> 0 | Q14: =P14*IF(N14=1,D14,0) -> 0
I15: =IF(AND(N(B15)>0,N(C15)>0),1,0) -> 0 | J15: =IF(I15=1,B15,0) -> 0 | K15: =IF($J$17>0,J15/$J$17,0) -> 0 | L15: =K15*IF(I15=1,C15,0) -> 0 | N15: =IF(AND(N(B15)>0,N(D15)>0),1,0) -> 0 | O15: =IF(N15=1,B15,0) -> 0 | P15: =IF($O$17>0,O15/$O$17,0) -> 0 | Q15: =P15*IF(N15=1,D15,0) -> 0
I16: =IF(AND(N(B16)>0,N(C16)>0),1,0) -> 0 | J16: =IF(I16=1,B16,0) -> 0 | K16: =IF($J$17>0,J16/$J$17,0) -> 0 | L16: =K16*IF(I16=1,C16,0) -> 0 | N16: =IF(AND(N(B16)>0,N(D16)>0),1,0) -> 0 | O16: =IF(N16=1,B16,0) -> 0 | P16: =IF($O$17>0,O16/$O$17,0) -> 0 | Q16: =P16*IF(N16=1,D16,0) -> 0
A17: Total | B17: =SUM(B7:B16) -> 24500 | I17: =SUM(I7:I16) -> 4 | J17: =SUM(J7:J16) -> 22500 | K17: =SUM(K7:K16) -> 1 | L17: =SUM(L7:L16) -> 125.33333 | N17: =SUM(N7:N16) -> 2 | O17: =SUM(O7:O16) -> 14000 | P17: =SUM(P7:P16) -> 1 | Q17: =SUM(Q7:Q16) -> 771.42857
K18: ↑ always 100% | L18: ↑ sums to the portfolio WACI | P18: ↑ always 100% | Q18: ↑ sums to the portfolio WACI
A20: Step 4 – Results
A21: Measure | B21: How it's worked out | C21: Scope 1+2 | D21: Scope 1+2+3
A22: Total portfolio value | B22: Sum of all amounts | C22: =B17 -> 24500 | D22: =B17 -> 24500
A23: Value with a figure | B23: Sum of amounts for funds with a WACI | C23: =J17 -> 22500 | D23: =O17 -> 14000
A24: Portfolio coverage | B24: Value with a figure ÷ total value | C24: =IF(B17>0,J17/B17,0) -> 0.91836735 | D24: =IF(B17>0,O17/B17,0) -> 0.57142857
A25: Portfolio WACI | B25: Sum of contributions (share × WACI) | C25: =L17 -> 125.33333 | D25: =Q17 -> 771.42857
A26: Cross-check | B26: Value-weighted average of WACI, worked out a second way | C26: =IF(J17>0,SUMPRODUCT(J7:J16,C7:C16)/J17,0) -> 125.33333 | D26: =IF(O17>0,SUMPRODUCT(O7:O16,D7:D16)/O17,0) -> 771.42857
A27: Coverage check | B27: 70% or more = reliable; below = indicative only | C27: =IF(J17=0,"No figures",IF(C24>=0.7,"OK (70% or more)","Indicative only (below 70%)")) -> OK (70% or more) | D27: =IF(O17=0,"No figures",IF(D24>=0.7,"OK (70% or more)","Indicative only (below 70%)")) -> Indicative only (below 70%)
A28: WACI currency | B28: Are all figures per $1m, all per €1m, or mixed? | C28: =IF(SUM(I7:I16)=0,"-",IF(AND(COUNTIFS(E7:E16,"USD",I7:I16,1)>0,COUNTIFS(E7:E16,"EUR",I7:I16,1)>0),"Mixed $ and € – approximate",IF(COUNTIFS(E7:E16,"EUR",I7:I16,1)>0,"All per €1m revenue","All per $1m revenue"))) -> All per $1m revenue | D28: =IF(SUM(N7:N16)=0,"-",IF(AND(COUNTIFS(E7:E16,"USD",N7:N16,1)>0,COUNTIFS(E7:E16,"EUR",N7:N16,1)>0),"Mixed $ and € – approximate",IF(COUNTIFS(E7:E16,"EUR",N7:N16,1)>0,"All per €1m revenue","All per $1m revenue"))) -> All per $1m revenue
A29: Fund data coverage (weighted) | B29: Average of each fund's reported coverage, weighted by value | C29: =IFERROR(SUMPRODUCT(J7:J16,F7:F16)/SUMIFS(J7:J16,F7:F16,">0"),"Not reported") -> 0.97777778 | D29: =IFERROR(SUMPRODUCT(O7:O16,F7:F16)/SUMIFS(O7:O16,F7:F16,">0"),"Not reported") -> 0.97857143
A30: Oldest figure date | B30: Earliest date among funds used | C30: =IF(COUNTIFS(I7:I16,1,G7:G16,">0")=0,"No dates",_xlfn.MINIFS(G7:G16,I7:I16,1,G7:G16,">0")) -> 46203 | D30: =IF(COUNTIFS(N7:N16,1,G7:G16,">0")=0,"No dates",_xlfn.MINIFS(G7:G16,N7:N16,1,G7:G16,">0")) -> 46234
A31: Funds with no figure for either scope | B31: Number of funds (Scope 1+2 column) and their value (Scope 1+2+3 column) | C31: =COUNTIFS(A7:A16,"<>",I7:I16,0,N7:N16,0,B7:B16,">0") -> 1 | D31: =SUMIFS(B7:B16,I7:I16,0,N7:N16,0) -> 2000
A33: Unit: tCO2e per $1m or €1m of company revenue, as the funds publish it. No currency conversion is applied.

Sheet How it works
A1: How the calculation works, using the example's numbers
A2: Green numbers are linked live from the 'WACI calculation' tab, so they change when you change the inputs.
A4: Step | B4: What happens | C4: Formula in words | D4: In the example
A5: 1 | B5: Add up the whole portfolio. | C5: Total value = sum of all amounts | D5: ='WACI calculation'!C22 -> 24500
A6: 2 | B6: Keep only the funds that publish a Scope 1+2 WACI. The bond fund has none, so it drops out. | C6: Value with a figure = sum of amounts for those funds | D6: ='WACI calculation'!C23 -> 22500
A7: 3 | B7: Work out how much of the portfolio has data. | C7: Coverage = value with a figure ÷ total value | D7: ='WACI calculation'!C24 -> 0.91836735
A8: 4 | B8: Rescale each fund's share so the funds with data add up to 100%. Example: the Global Equity fund's share. | C8: Share = fund amount ÷ value with a figure | D8: ='WACI calculation'!K7 -> 0.44444444
A9: 5 | B9: Multiply each fund's share by its WACI. Example: the Global Equity fund's contribution. | C9: Contribution = share × fund WACI | D9: ='WACI calculation'!L7 -> 42.222222
A10: 6 | B10: Add up the contributions. This is the portfolio WACI. | C10: Portfolio WACI = sum of contributions | D10: ='WACI calculation'!C25 -> 125.33333
A11: 7 | B11: Check the result is reliable enough. | C11: Coverage of 70% or more = OK; below = indicative only | D11: ='WACI calculation'!C27 -> OK (70% or more)
A12: 8 | B12: Repeat steps 2–7 for Scope 1+2+3, keeping it separate. Only two example funds report it, so coverage falls below 70%. | C12: Same method, Scope 1+2+3 column | D12: ='WACI calculation'!D25 -> 771.42857
A13: 8b | B13: Scope 1+2+3 coverage check. | C13: Same 70% rule | D13: ='WACI calculation'!D27 -> Indicative only (below 70%)
A15: Why rescale? A fund without a figure isn't assumed to be zero or average. It's simply left out, and coverage tells you how much was left out.
A16: Why keep scopes apart? Scope 3 figures are typically several times larger than Scope 1+2, so blending them would distort the result.
A17: Why no currency conversion? Funds publish WACI per $1m or per €1m of revenue. Version 1 uses figures exactly as published and flags any mix.
